MANIFEST.in
README.rst
setup.py
webassets_ext/__init__.py
webassets_jinja2js.egg-info/PKG-INFO
webassets_jinja2js.egg-info/SOURCES.txt
webassets_jinja2js.egg-info/dependency_links.txt
webassets_jinja2js.egg-info/requires.txt
webassets_jinja2js.egg-info/top_level.txt