Metadata-Version: 1.0
Name: webassets-jinja2js
Version: 1.0.0
Summary: Integration of pwt.jinja2js compiler with the webassets package.
Home-page: https://pypi.python.org/pypi/webassets-jinja2js/
Author: Michael Su
Author-email: mdasu1@gmail.com
License: BSD
Platform: UNKNOWN
Classifier: Development Status :: 5 - Production/Stable
Classifier: Environment :: Web Environment
Classifier: License :: OSI Approved :: BSD License
Classifier: Topic :: Internet :: WWW/HTTP :: Site Management
